ovos_skill_spotify/CHANGELOG.md
ovos_skill_spotify/MANIFEST.in
ovos_skill_spotify/README.md
ovos_skill_spotify/__init__.py
ovos_skill_spotify/requirements.txt
ovos_skill_spotify/spotify.png
ovos_skill_spotify/spotify.py
ovos_skill_spotify/version.py
ovos_skill_spotify/locale/ca-es/spotify_skill.voc
ovos_skill_spotify/locale/da-dk/spotify_skill.voc
ovos_skill_spotify/locale/de-de/spotify_skill.voc
ovos_skill_spotify/locale/en-us/spotify_skill.voc
ovos_skill_spotify/locale/es-es/spotify_skill.voc
ovos_skill_spotify/locale/fr-fr/spotify_skill.voc
ovos_skill_spotify/locale/gl-es/spotify_skill.voc
ovos_skill_spotify/locale/it-it/spotify_skill.voc
ovos_skill_spotify/locale/nl-nl/spotify_skill.voc
ovos_skill_spotify/locale/pl-pl/spotify_skill.voc
ovos_skill_spotify/locale/pt-br/spotify_skill.voc
ovos_skill_spotify/locale/ru-ru/spotify_skill.voc
ovos_skill_spotify/locale/sv-se/spotify_skill.voc
ovos_skill_spotify/ovos_skill_spotify.egg-info/PKG-INFO
ovos_skill_spotify/ovos_skill_spotify.egg-info/SOURCES.txt
ovos_skill_spotify/ovos_skill_spotify.egg-info/dependency_links.txt
ovos_skill_spotify/ovos_skill_spotify.egg-info/entry_points.txt
ovos_skill_spotify/ovos_skill_spotify.egg-info/requires.txt
ovos_skill_spotify/ovos_skill_spotify.egg-info/top_level.txt
ovos_skill_spotify-0.1.10.dist-info/METADATA
ovos_skill_spotify-0.1.10.dist-info/WHEEL
ovos_skill_spotify-0.1.10.dist-info/entry_points.txt
ovos_skill_spotify-0.1.10.dist-info/top_level.txt
ovos_skill_spotify-0.1.10.dist-info/RECORD
