Metadata-Version: 2.1
Name: ovos-skill-spotify
Version: 0.1.10
Home-page: https://github.com/OpenVoiceOS/ovos-skill-spotify
License: Apache-2.0
Keywords: ovos skill plugin
Requires-Dist: ovos-utils>=0.5.0
Requires-Dist: ovos-bus-client<2.0.0,>=0.0.9
Requires-Dist: ovos-workshop<8.0.0,>=0.0.16
Requires-Dist: spotipy
